test_pip_install/__init__.py
test_pip_install/__main__.py
test_pip_install-0.0.3.dist-info/COPYING.LESSER
test_pip_install-0.0.3.dist-info/LICENSE
test_pip_install-0.0.3.dist-info/METADATA
test_pip_install-0.0.3.dist-info/WHEEL
test_pip_install-0.0.3.dist-info/entry_points.txt
test_pip_install-0.0.3.dist-info/top_level.txt
test_pip_install-0.0.3.dist-info/RECORD
