Metadata-Version: 2.1
Name: test-pip-install
Version: 0.0.3
Summary: Test if `pip install` is working
Home-page: https://github.com/niess/test-pip-install
Author: Valentin Niess
Author-email: valentin.niess@gmail.com
License: UNKNOWN
Platform: UNKNOWN
Classifier: Programming Language :: Python
Classifier: Development Status :: 4 - Beta
Classifier: License :: OSI Approved :: GNU Lesser General Public License v3 (LGPLv3)
Classifier: Natural Language :: English
Classifier: Operating System :: OS Independent
Classifier: Topic :: Software Development :: Testing
